filepreview
