Metadata-Version: 1.0
Name: django-filepreview
Version: 0.1.1
Summary: Autogenerated file preview field for django files
Home-page: https://github.com/basxsoftwareassociation/django-filepreview
Author: basx Software Association
Author-email: info@basx.dev
License: New BSD License
Platform: UNKNOWN
